coco_lm_pytorch/__init__.py
coco_lm_pytorch/coco_lm_pytorch.py
coco_lm_pytorch-0.0.2.dist-info/LICENSE
coco_lm_pytorch-0.0.2.dist-info/METADATA
coco_lm_pytorch-0.0.2.dist-info/WHEEL
coco_lm_pytorch-0.0.2.dist-info/top_level.txt
coco_lm_pytorch-0.0.2.dist-info/RECORD
