Metadata-Version: 2.1
Name: coco-lm-pytorch
Version: 0.0.2
Summary: COCO - Pytorch
Home-page: https://github.com/lucidrains/coco-lm-pytorch
Author: Phil Wang
Author-email: lucidrains@gmail.com
License: MIT
Keywords: transformers,artificial intelligence,deep learning,pretraining
Platform: UNKNOWN
Classifier: Development Status :: 4 - Beta
Classifier: Intended Audience :: Developers
Classifier: Topic :: Scientific/Engineering :: Artificial Intelligence
Classifier: License :: OSI Approved :: MIT License
Classifier: Programming Language :: Python :: 3.7
Requires-Dist: torch (>=1.6.0)
Requires-Dist: einops
Requires-Dist: x-transformers
